[
    //
    // General keybindings
    //

    {
        "key":     "ctrl+alt+l",
        "command": "-editor.foldRecursively",
        "when":    "editorTextFocus"
    },
    {
        "key":     "shift+alt+f",
        "command": "-editor.foldRecursively",
        "when":    "editorTextFocus"
    },
    {
        "key":     "ctrl+alt+l",
        "command": "-editor.action.formatDocument",
        "when":    "editorHasDocumentFormattingProvider && editorHasDocumentFormattingProvider && editorTextFocus && !editorReadonly"
    },
    {
        "key":     "ctrl+shift+a",
        "command": "workbench.action.toggleActivityBarVisibility"
    },
    {
        "key":     "alt+`",
        "command": "workbench.action.toggleSidebarVisibility"
    },
    
    //
    //  Vim-like keybindings
    //

    // Pane movement
    {
        "key":     "alt+k",
        "command": "workbench.action.navigateUp"
    },
    {
        "key":     "alt+j",
        "command": "workbench.action.navigateDown"
    },
    {
        "key":     "alt+h",
        "command": "workbench.action.navigateLeft"
    },
    {
        "key":     "alt+l",
        "command": "workbench.action.navigateRight"
    },

    // Buffer movement
    {
        "key":     "alt+n",
        "command": "workbench.action.nextEditorInGroup"
    },
    {
        "key":     "alt+p",
        "command": "workbench.action.previousEditorInGroup"
    },
    
    // General
    {
        "key":     "alt+v",
        "command": "workbench.action.splitEditor"
    },
    {
        "key":     "alt+s",
        "command": "workbench.action.splitEditorOrthogonal"
    },
    {
        "key":     "alt+w",
        "command": "workbench.action.closeActiveEditor"
    },
    {
        "key":     "alt+q",
        "command": "workbench.action.closeEditorsAndGroup"
    }
]